odoo/addons/sommobilitat/__init__.py
odoo/addons/sommobilitat/__manifest__.py
odoo/addons/sommobilitat/controllers/__init__.py
odoo/addons/sommobilitat/controllers/controllers.py
odoo/addons/sommobilitat/migrations/12.0.1.2/post-migration.py
odoo/addons/sommobilitat/migrations/12.0.1.2/pre-migration.py
odoo/addons/sommobilitat/models/__init__.py
odoo/addons/sommobilitat/models/models_sm_cron.py
odoo/addons/sommobilitat/models/models_sm_maintenance_user.py
odoo/addons/sommobilitat/models/models_sm_member.py
odoo/addons/sommobilitat/models/models_sm_member_fetch_wizard.py
odoo/addons/sommobilitat/models/models_sommobilitat_utils.py
odoo/addons/sommobilitat/security/ir.model.access.csv
odoo/addons/sommobilitat/security/sommobilitat_security.xml
odoo/addons/sommobilitat/services/__init__.py
odoo/addons/sommobilitat/services/partner_services.py
odoo/addons/sommobilitat/views/views.xml
odoo/addons/sommobilitat/views/views_cron.xml
odoo/addons/sommobilitat/views/views_members.xml
odoo/addons/sommobilitat/views/views_members_actions.xml
odoo/addons/sommobilitat/views/views_members_fetch_wizard.xml
odoo12_addon_sommobilitat-12.0.0.0.3.dist-info/METADATA
odoo12_addon_sommobilitat-12.0.0.0.3.dist-info/WHEEL
odoo12_addon_sommobilitat-12.0.0.0.3.dist-info/top_level.txt
odoo12_addon_sommobilitat-12.0.0.0.3.dist-info/RECORD
